MANIFEST.in
README.txt
setup.py
django_buzz.egg-info/PKG-INFO
django_buzz.egg-info/SOURCES.txt
django_buzz.egg-info/dependency_links.txt
django_buzz.egg-info/top_level.txt
pystories/__init__.py
pystories/admin.py
pystories/fetchffeed.py
pystories/models.py
pystories/urls.py
pystories/views.py
pystories/migrations/0001_initial.py
pystories/migrations/0002_topic.py
pystories/migrations/0003_uniqueness.py
pystories/migrations/__init__.py
pystories/services/EntryService.py
pystories/services/__init__.py
pystories/templates/pystories/base.html
pystories/templates/pystories/index.html
pystories/templates/pystories/onlywidget.html
pystories/templates/pystories/feeds/description.html
pystories/templates/pystories/feeds/title.html