Metadata-Version: 1.0
Name: django-buzz
Version: 0.1.2
Summary: Django app to find What is hot and buzzing in a topic.
Home-page: http://github.com/agiliq/django-buzz
Author: Agiliq and friends
Author-email: shabda@agiliq.com
License: UNKNOWN
Platform: UNKNOWN
